CHANGELOG.md
LICENSE.txt
MANIFEST.in
README.md
requirements.txt
setup.cfg
setup.py
test_requirements.txt
gitcommonsync/__init__.py
gitcommonsync/_ansible_runner.py
gitcommonsync/_common.py
gitcommonsync/ansible_module.py
gitcommonsync/helpers.py
gitcommonsync/models.py
gitcommonsync/repository.py
gitcommonsync/synchronisers.py
gitcommonsync.egg-info/PKG-INFO
gitcommonsync.egg-info/SOURCES.txt
gitcommonsync.egg-info/dependency_links.txt
gitcommonsync.egg-info/requires.txt
gitcommonsync.egg-info/top_level.txt
gitcommonsync/tests/__init__.py
gitcommonsync/tests/_common.py
gitcommonsync/tests/test_ansible_module.py
gitcommonsync/tests/test_repository.py
gitcommonsync/tests/test_synchronise.py
gitcommonsync/tests/resources/__init__.py
gitcommonsync/tests/resources/information.py