Metadata-Version: 1.0
Name: gitcommonsync
Version: 2.0.0
Summary: A tool to synchronise common files between Git repositories
Home-page: https://github.com/wtsi-hgi/git-common-sync
Author: UNKNOWN
Author-email: UNKNOWN
License: MIT
Platform: UNKNOWN
